aurorabot/__init__.py
aurorabot/bot.py
aurorabot/cosmetic.py
aurorabot/cosmeticshortcuts.py
aurorabot/deviceauths.py
aurorabot/errors.py
aurorabot/events.py
aurorabot/generator.py
aurorabot/owner.py
aurorabot/party.py
aurorabot/settings.py
aurorabot-2.0.0.dist-info/LICENSE
aurorabot-2.0.0.dist-info/METADATA
aurorabot-2.0.0.dist-info/WHEEL
aurorabot-2.0.0.dist-info/top_level.txt
aurorabot-2.0.0.dist-info/RECORD
